{"cameraMode":{"drawMode":0,"name":"Shaded","section":"Shading Mode"},"sceneLighting":true,"audioPlay":false,"sceneViewState":{"showFog":true,"showMaterialUpdate":false,"showSkybox":true,"showFlares":true,"showImageEffects":true,"showParticleSystems":true,"showVisualEffectGraphs":true,"m_FxEnabled":true},"in2DMode":false,"pivot":{"x":9.828485488891602,"y":-1.0067415237426758,"z":-4.480964660644531},"rotation":{"x":-0.02097383886575699,"y":0.9635592103004456,"z":-0.25458431243896487,"w":-0.07938238978385925},"size":10.0,"orthographic":false}